{
	"devices": [
		{
			"id": "device_0",
			"name": "Router 1",
			"hardware": "C2000",
			"slots": [
				{
					"id": 0,
					"model": "E2000",
					"editable": false
				},
				{
					"id": 1,
					"model": "E2100",
					"editable": true
				},
				{
					"id": 3,
					"model": null,
					"editable": true
				}
			],
			"ajaxterm-url": "http://example.com/users/vasya/app/mynet/R1.html",
			"metadata": {
				"position": {
					"x": 123,
					"y": 100
				}
			}
		},
		{
			"id": "device_1",
			"name": "Computer",
			"hardware": "VM",
			"slots": [
				{
					"id": 0,
					"model": "Realtek",
					"editable": false
				}
			],
			"ajaxterm-url": "http://example.com/users/vasya/app/mynet/M1.html",
			"metadata": {
				"position": {
					"x": 200,
					"y": 200
				}
			}
		}
	],
	"wires": [
	    {
	    	"id": "wire_0",
	    	"left": {"device": "device_0", "slot": 0, "port": 0},
	    	"right": {"device": "device_1", "slot": 0, "port": 0}
	    }
	]
}
